{
    "conf_path": "./public/config.ini",
    "env_path": "./.env",
    "market_symbol": "FTT/USD",
    "sub_account": "FTT_RB",
    "trig_price_chg_thresh": 10.0,
    "base_ratio_min": 0.4,
    "base_ratio_max": 0.6,
    "timeframe_rb": "4h",
    "ema1_len": 5,
    "ema2_len": 10,
    "timeframe_ratio": "1d",
    "rsi_len": 14,
    "ftx_client": "<modules.ftx_client.FtxClient object at 0x000001B720A557B0>",
    "base_symbol": "FTT",
    "quote_symbol": "USD",
    "market_info": {
        "name": "FTT/USD",
        "enabled": true,
        "postOnly": false,
        "priceIncrement": 0.001,
        "sizeIncrement": 0.1,
        "minProvideSize": 0.1,
        "last": 29.191,
        "bid": 29.185,
        "ask": 29.191,
        "price": 29.191,
        "type": "spot",
        "futureType": null,
        "baseCurrency": "FTT",
        "isEtfMarket": false,
        "quoteCurrency": "USD",
        "underlying": null,
        "restricted": false,
        "highLeverageFeeExempt": true,
        "largeOrderThreshold": 350.0,
        "change1h": 0.0012691225903821088,
        "change24h": 0.040121147336540174,
        "changeBod": 0.016470506302667318,
        "quoteVolume24h": 19236953.8215,
        "volumeUsd24h": 19236953.8215,
        "priceHigh24h": 29.522,
        "priceLow24h": 27.755
    },
    "init_price": 29.191,
    "base_balance": {
        "coin": "FTT",
        "total": 0.3,
        "free": 0.3,
        "availableForWithdrawal": 0.3,
        "availableWithoutBorrow": 0.3,
        "usdValue": 8.7567,
        "spotBorrow": 0.0
    },
    "quote_balance": {
        "coin": "USD",
        "total": 92.90566474,
        "free": 92.90566474,
        "availableForWithdrawal": 92.90566474,
        "availableWithoutBorrow": 92.90566474,
        "usdValue": 92.905664744965,
        "spotBorrow": 0.0
    },
    "init_nav": 101.66236474496499,
    "last_rb_price": -1,
    "datetime": "25/07/2022 00:10:47",
    "price": 29.191,
    "price_chg_pct": 0.0,
    "base_balance_value": 8.7567,
    "quote_balance_value": 92.905664744965,
    "nav": 101.66236474496499,
    "base_balance_value_ratio": 0.08613512012992686,
    "base_balance_value_ratio_pct": 8.61,
    "nav_pct": 100.0,
    "last_rb_price_chg_pct": -3019.1
}